{"cameraMode":{"drawMode":0,"name":"Shaded","section":"Shading Mode"},"sceneLighting":false,"audioPlay":false,"sceneViewState":{"m_AlwaysRefresh":false,"showFog":true,"showSkybox":false,"showFlares":true,"showImageEffects":true,"showParticleSystems":true,"showVisualEffectGraphs":true,"m_FxEnabled":true},"in2DMode":false,"pivot":{"x":-4.528750419616699,"y":-5.440855979919434,"z":-16.243688583374025},"rotation":{"x":-0.02057831548154354,"y":0.9778552055358887,"z":-0.172790065407753,"w":-0.11640477180480957},"size":20.801551818847658,"orthographic":false}